poetry_plugin_drop_python_upper_constraint/__init__.py
poetry_plugin_drop_python_upper_constraint/py.typed
poetry_plugin_drop_python_upper_constraint-1.0.1.dist-info/LICENSE
poetry_plugin_drop_python_upper_constraint-1.0.1.dist-info/METADATA
poetry_plugin_drop_python_upper_constraint-1.0.1.dist-info/WHEEL
poetry_plugin_drop_python_upper_constraint-1.0.1.dist-info/entry_points.txt
poetry_plugin_drop_python_upper_constraint-1.0.1.dist-info/RECORD
